{"filter": [{"Filter Type": "PREAMP", "Frequency(Hz)": null, "Gain(dB)": -4.5, "Q-Factor": null, "BW": null}, {"Filter Type": "PEAK", "Frequency(Hz)": 48.0, "Gain(dB)": -6.5, "Q-Factor": 0.5, "BW": 2.54}, {"Filter Type": "LOW_SHELF", "Frequency(Hz)": 105.0, "Gain(dB)": 5.5, "Q-Factor": 0.71, "BW": null}, {"Filter Type": "PEAK", "Frequency(Hz)": 125.0, "Gain(dB)": -2.5, "Q-Factor": 2.0, "BW": 0.71}, {"Filter Type": "PEAK", "Frequency(Hz)": 200.0, "Gain(dB)": 2.0, "Q-Factor": 2.0, "BW": 0.71}, {"Filter Type": "PEAK", "Frequency(Hz)": 2600.0, "Gain(dB)": -2.8, "Q-Factor": 1.7, "BW": 0.84}, {"Filter Type": "HIGH_SHELF", "Frequency(Hz)": 3000.0, "Gain(dB)": 2.8, "Q-Factor": 0.71, "BW": null}, {"Filter Type": "PEAK", "Frequency(Hz)": 3900.0, "Gain(dB)": -1.0, "Q-Factor": 6.0, "BW": 0.24}, {"Filter Type": "PEAK", "Frequency(Hz)": 5700.0, "Gain(dB)": -5.0, "Q-Factor": 4.5, "BW": 0.32}, {"Filter Type": "PEAK", "Frequency(Hz)": 8100.0, "Gain(dB)": -3.7, "Q-Factor": 6.0, "BW": 0.24}, {"Filter Type": "HIGH_SHELF", "Frequency(Hz)": 10000.0, "Gain(dB)": -2.0, "Q-Factor": 0.71, "BW": null}], "extra": {"Deviation from Target": "1,20 dB 0,72 dB", "Preference Rating": "87/100 96/100"}, "info": {"Hash": "315ea04ad1b14a33d73da7373abc57b2", "Script Version": 0.1}}