{"filter": [{"Filter Type": "PREAMP", "Frequency(Hz)": null, "Gain(dB)": -11.3, "Q-Factor": null, "BW": null}, {"Filter Type": "PEAK", "Frequency(Hz)": 200.0, "Gain(dB)": -6.3, "Q-Factor": 0.38, "BW": 3.14}, {"Filter Type": "PEAK", "Frequency(Hz)": 400.0, "Gain(dB)": 1.2, "Q-Factor": 1.5, "BW": 0.94}, {"Filter Type": "PEAK", "Frequency(Hz)": 800.0, "Gain(dB)": 3.3, "Q-Factor": 0.82, "BW": 1.67}, {"Filter Type": "PEAK", "Frequency(Hz)": 1150.0, "Gain(dB)": -0.4, "Q-Factor": 4.0, "BW": 0.36}, {"Filter Type": "PEAK", "Frequency(Hz)": 1700.0, "Gain(dB)": -4.4, "Q-Factor": 0.9, "BW": 1.53}, {"Filter Type": "PEAK", "Frequency(Hz)": 2550.0, "Gain(dB)": 0.9, "Q-Factor": 3.0, "BW": 0.48}, {"Filter Type": "PEAK", "Frequency(Hz)": 3250.0, "Gain(dB)": 13.0, "Q-Factor": 0.85, "BW": 1.61}, {"Filter Type": "PEAK", "Frequency(Hz)": 5250.0, "Gain(dB)": -1.7, "Q-Factor": 5.0, "BW": 0.29}, {"Filter Type": "HIGH_SHELF", "Frequency(Hz)": 7000.0, "Gain(dB)": -10.0, "Q-Factor": 0.7, "BW": 0.36}, {"Filter Type": "PEAK", "Frequency(Hz)": 13000.0, "Gain(dB)": 4.0, "Q-Factor": 2.0, "BW": 0.71}], "extra": {"Deviation from Target": "3,99 dB 0,54 dB", "Preference Rating": "49/100 96/100"}, "info": {"Hash": "25af8ff6f031b4a4a96596a7cb7ef230", "Script Version": 0.1}}