{"filter": [{"Filter Type": "PREAMP", "Frequency(Hz)": null, "Gain(dB)": -8.5, "Q-Factor": null, "BW": null}, {"Filter Type": "LOW_SHELF", "Frequency(Hz)": 40.0, "Gain(dB)": 3.0, "Q-Factor": 0.71, "BW": null}, {"Filter Type": "LOW_SHELF", "Frequency(Hz)": 105.0, "Gain(dB)": 5.5, "Q-Factor": 0.71, "BW": null}, {"Filter Type": "PEAK", "Frequency(Hz)": 520.0, "Gain(dB)": 1.9, "Q-Factor": 1.4, "BW": 1.01}, {"Filter Type": "PEAK", "Frequency(Hz)": 1100.0, "Gain(dB)": -3.9, "Q-Factor": 1.0, "BW": 1.39}, {"Filter Type": "HIGH_SHELF", "Frequency(Hz)": 1400.0, "Gain(dB)": 7.0, "Q-Factor": 0.71, "BW": null}, {"Filter Type": "PEAK", "Frequency(Hz)": 2500.0, "Gain(dB)": -1.0, "Q-Factor": 2.5, "BW": 0.57}, {"Filter Type": "PEAK", "Frequency(Hz)": 5300.0, "Gain(dB)": -8.0, "Q-Factor": 3.3, "BW": 0.44}, {"Filter Type": "PEAK", "Frequency(Hz)": 8000.0, "Gain(dB)": 3.0, "Q-Factor": 1.4, "BW": 1.01}, {"Filter Type": "HIGH_SHELF", "Frequency(Hz)": 10000.0, "Gain(dB)": -10.0, "Q-Factor": 0.71, "BW": null}], "extra": {"Deviation from Target": "3,11 dB 0,49 dB", "Preference Rating": "67/100 99/100"}, "info": {"Hash": "451ae71a75420e92f87a5188065c74f9", "Script Version": 0.1}}