{"filter": [{"Filter Type": "PREAMP", "Frequency(Hz)": null, "Gain(dB)": -4.6, "Q-Factor": null, "BW": null}, {"Filter Type": "PEAK", "Frequency(Hz)": 20.0, "Gain(dB)": 3.0, "Q-Factor": 1.5, "BW": 0.94}, {"Filter Type": "PEAK", "Frequency(Hz)": 150.0, "Gain(dB)": -3.0, "Q-Factor": 1.0, "BW": 1.39}, {"Filter Type": "PEAK", "Frequency(Hz)": 320.0, "Gain(dB)": 2.9, "Q-Factor": 1.5, "BW": 0.94}, {"Filter Type": "PEAK", "Frequency(Hz)": 950.0, "Gain(dB)": -3.6, "Q-Factor": 0.9, "BW": 1.53}, {"Filter Type": "PEAK", "Frequency(Hz)": 3600.0, "Gain(dB)": -3.9, "Q-Factor": 3.0, "BW": 0.48}, {"Filter Type": "PEAK", "Frequency(Hz)": 5200.0, "Gain(dB)": 5.5, "Q-Factor": 1.0, "BW": 1.39}, {"Filter Type": "PEAK", "Frequency(Hz)": 9200.0, "Gain(dB)": -7.7, "Q-Factor": 4.0, "BW": 0.36}], "extra": {"Deviation from Target": "1,97 dB 0,41 dB", "Preference Rating": "78/100 107/100"}, "info": {"Hash": "3b49d2f466c52237900b758fa47107dd", "Script Version": 0.1}}