{"filter": [{"Filter Type": "PREAMP", "Frequency(Hz)": null, "Gain(dB)": -5.5, "Q-Factor": null, "BW": null}, {"Filter Type": "PEAK", "Frequency(Hz)": 80.0, "Gain(dB)": -2.2, "Q-Factor": 0.7, "BW": 1.92}, {"Filter Type": "LOW_SHELF", "Frequency(Hz)": 105.0, "Gain(dB)": 5.5, "Q-Factor": 0.71, "BW": null}, {"Filter Type": "PEAK", "Frequency(Hz)": 1320.0, "Gain(dB)": -6.5, "Q-Factor": 1.4, "BW": 1.01}, {"Filter Type": "HIGH_SHELF", "Frequency(Hz)": 1550.0, "Gain(dB)": 3.0, "Q-Factor": 0.71, "BW": null}, {"Filter Type": "PEAK", "Frequency(Hz)": 2050.0, "Gain(dB)": 1.5, "Q-Factor": 3.0, "BW": 0.48}, {"Filter Type": "PEAK", "Frequency(Hz)": 2950.0, "Gain(dB)": -1.0, "Q-Factor": 3.0, "BW": 0.48}, {"Filter Type": "PEAK", "Frequency(Hz)": 3800.0, "Gain(dB)": 1.5, "Q-Factor": 3.0, "BW": 0.48}, {"Filter Type": "PEAK", "Frequency(Hz)": 5750.0, "Gain(dB)": -7.7, "Q-Factor": 3.0, "BW": 0.48}], "extra": {"Deviation from Target": "2,14 dB 0,59 dB", "Preference Rating": "80/100 93/100"}, "info": {"Hash": "a5134f12908aea44309d85f4771894c6", "Script Version": 0.1}}